wesutils/__init__.py
wesutils/agents.py
wesutils/utils.py
wesutils-0.0.7.dist-info/LICENSE
wesutils-0.0.7.dist-info/METADATA
wesutils-0.0.7.dist-info/WHEEL
wesutils-0.0.7.dist-info/top_level.txt
wesutils-0.0.7.dist-info/RECORD
