Metadata-Version: 2.1
Name: wesutils
Version: 0.0.7
Summary: my most commonly used utilities
Home-page: https://github.com/wessle/wesutils
Author: Wesley Suttle
License: UNKNOWN
Platform: UNKNOWN
Classifier: Programming Language :: Python :: 3
Classifier: License :: OSI Approved :: MIT License
Classifier: Operating System :: OS Independent
Requires-Python: >=3.6
Requires-Dist: numpy
Requires-Dist: torch
Requires-Dist: pyyaml
